keyrings/__init__.py
keyrings/aws.py
keyrings.aws_codeartifact_auth-0.0.2.dist-info/METADATA
keyrings.aws_codeartifact_auth-0.0.2.dist-info/WHEEL
keyrings.aws_codeartifact_auth-0.0.2.dist-info/entry_points.txt
keyrings.aws_codeartifact_auth-0.0.2.dist-info/top_level.txt
keyrings.aws_codeartifact_auth-0.0.2.dist-info/RECORD
