Metadata-Version: 2.1
Name: keyrings.aws-codeartifact-auth
Version: 0.0.2
Summary: Keyring backend for AWS auth
Author: Daniel Low
Requires-Python: >=3.6
Requires-Dist: keyring
